db_attribute/__init__.py
db_attribute/connector.py
db_attribute/db_class.py
db_attribute/db_types.py
db_attribute/db_work.py
db_attribute/discriptor.py
db_attribute-2.1.1.1.dist-info/licenses/LICENSE
db_attribute-2.1.1.1.dist-info/METADATA
db_attribute-2.1.1.1.dist-info/WHEEL
db_attribute-2.1.1.1.dist-info/top_level.txt
db_attribute-2.1.1.1.dist-info/RECORD
