Metadata-Version: 2.4
Name: db_attribute
Version: 2.1.1.1
Summary: DataBase attribute package
Home-page: https://github.com/shutkanos/Db-Attribute
Author: Shutkanos
Author-email: Shutkanos <Shutkanos836926@mail.ru>
License: MIT
Project-URL: Homepage, https://github.com/shutkanos/Db-Attribute
Project-URL: Documentation, https://github.com/shutkanos/Db-Attribute#readme.md
Project-URL: Repository, https://github.com/shutkanos/Db-Attribute
Keywords: db,database,attribute,db_attribute,db attribute,DbAttribute,database attribute,orm,ORM,attribute orm,attribute ORM,attr,attr ORM,attr orm,db attr,DbAttr
Classifier: Development Status :: 5 - Production/Stable
Classifier: Intended Audience :: Developers
Classifier: License :: OSI Approved :: MIT License
Classifier: Programming Language :: Python :: 3
Requires-Python: >=3.9
License-File: LICENSE
Requires-Dist: mysql-connector-python>=1.4
Requires-Dist: orjson
Dynamic: author
Dynamic: home-page
Dynamic: license-file
